categorizacao.v
module s1 (input p3, e1, e0, output s1_saida);
    nor(s1_saida, p3, e1, e0);
endmodule
module s2(input p3, p2, p1, p0, e1, e0, output s2_saida);
    wire np3, np2, ne1, z1, z2, z3;
    nor(z1, p1, p0);
    not(np3, p3);
    not(np2, p2);
    not(ne1, e1);
    or(z3, np3, np2, z1);
    and(z2, ne1, e0);
    and(s2_saida, z3, z2);
endmodule
module s3(input p3, p2, p1, p0, e1, output s3_saida);
    wire z1, z2, z3;
    and(z1, p3, p2);
    or(z2, p1, p0);
    and(z3, z2, z1);
    and(s3_saida, z3, e1);
endmodule
module error(input c1, c2, c3, output e_saida);
    nor(e_saida, c1, c2, c3);
endmodule
module circuito (
    input p3, p2, p1, p0, e1, e0,
    output c1, c2, c3, E
);

    s1 U1 (.p3(p3), .e1(e1), .e0(e0), .s1_saida(c1));
    s2 U2 (.p3(p3), .p2(p2), .p1(p1), .p0(p0), .e1(e1), .e0(e0), .s2_saida(c2));
    s3 U3 (.p3(p3), .p2(p2), .p1(p1), .p0(p0), .e1(e1), .s3_saida(c3));
    error U4 (.c1(c1), .c2(c2), .c3(c3), .e_saida(E));
endmodule

tb_completo.v
module tb_circuito;
    reg p3, p2, p1, p0, e1, e0;
    wire c1, c2, c3, E;

    // CORREÇÃO DO ERRO: Declara e atribui variáveis intermediárias
    // para que o $monitor possa imprimi-las.
    wire [3:0] peso;
    wire [1:0] eixo;
    assign peso = {p3, p2, p1, p0};
    assign eixo = {e1, e0};
    
    // Instancia o Circuito Principal (DUT)
    circuito DUT (.p3(p3), .p2(p2), .p1(p1), .p0(p0), .e1(e1), .e0(e0),
                  .c1(c1), .c2(c2), .c3(c3), .E(E));

    initial begin
        // Agora usamos as variáveis 'peso' e 'eixo' no monitor
        $monitor("t=%0d | P=%b%b%b%b (%0d) Eixo=%b%b (%0d) | C1=%b C2=%b C3=%b E=%b",
                  $time, p3, p2, p1, p0, peso, e1, e0, eixo, c1, c2, c3, E);

        // Define o formato VCD para visualização gráfica no GTKWave (opcional, mas bom)
        $dumpfile("ondas.vcd");
        $dumpvars(0, tb_circuito); 

        // ----------------------------------------------------
        // CASOS DE TESTE COBRINDO TODAS AS REGRAS E ERROS
        // ----------------------------------------------------

        // Inicializa entradas
        p3=0; p2=0; p1=0; p0=0; e1=0; e0=0; // T0: P=0 (<=7) Eixo=00 -> C1
        #10; 

        // --- Testes C1 (Peso <= 7 E Eixo = 00) ---
        p3=0; p2=1; p1=0; p0=0; e1=0; e0=0; // P=4 (<=7) Eixo=00 -> C1
        #10;
        
        // --- Testes C2 (Peso <= 12 E Eixo = 01) ---
        p3=1; p2=0; p1=0; p0=0; e1=0; e0=1; // P=8 (<=12) Eixo=01 -> C2
        #10;
        p3=1; p2=1; p1=0; p0=0; e1=0; e0=1; // P=12 (<=12) Eixo=01 -> C2
        #10;

        // --- Testes C3 (Peso > 12 E Eixo >= 10) ---
        p3=1; p2=1; p1=0; p0=1; e1=1; e0=0; // P=13 (>12) Eixo=10 -> C3
        #10;
        p3=1; p2=1; p1=1; p0=1; e1=1; e0=1; // P=15 (>12) Eixo=11 -> C3
        #10;

        // --- Testes Erro (Situações de falha de regra) ---
        p3=1; p2=0; p1=0; p0=0; e1=0; e0=0; // P=8 (>7) Eixo=00 -> Erro (Peso falha C1)
        #10;
        p3=0; p2=1; p1=1; p0=1; e1=0; e0=1; // P=7 (<=7) Eixo=01 -> Erro (Eixo falha C1, Peso falha C2)
        #10;
        p3=0; p2=0; p1=0; p0=1; e1=1; e0=1; // P=1 Eixo=11 -> Erro (Nenhuma regra atende)
        #10;
        
        $finish;
    end
endmodule

ondas.vcd
$date
	Mon Oct 13 17:13:12 2025
$end
$version
	Icarus Verilog
$end
$timescale
	1s
$end
$scope module tb_circuito $end
$var wire 4 ! peso [3:0] $end
$var wire 2 " eixo [1:0] $end
$var wire 1 # c3 $end
$var wire 1 $ c2 $end
$var wire 1 % c1 $end
$var wire 1 & E $end
$var reg 1 ' e0 $end
$var reg 1 ( e1 $end
$var reg 1 ) p0 $end
$var reg 1 * p1 $end
$var reg 1 + p2 $end
$var reg 1 , p3 $end
$scope module DUT $end
$var wire 1 ' e0 $end
$var wire 1 ( e1 $end
$var wire 1 ) p0 $end
$var wire 1 * p1 $end
$var wire 1 + p2 $end
$var wire 1 , p3 $end
$var wire 1 # c3 $end
$var wire 1 $ c2 $end
$var wire 1 % c1 $end
$var wire 1 & E $end
$scope module U1 $end
$var wire 1 ' e0 $end
$var wire 1 ( e1 $end
$var wire 1 , p3 $end
$var wire 1 % s1_saida $end
$upscope $end
$scope module U2 $end
$var wire 1 ' e0 $end
$var wire 1 ( e1 $end
$var wire 1 - ne1 $end
$var wire 1 . np2 $end
$var wire 1 / np3 $end
$var wire 1 ) p0 $end
$var wire 1 * p1 $end
$var wire 1 + p2 $end
$var wire 1 , p3 $end
$var wire 1 $ s2_saida $end
$var wire 1 0 z1 $end
$var wire 1 1 z2 $end
$var wire 1 2 z3 $end
$upscope $end
$scope module U3 $end
$var wire 1 ( e1 $end
$var wire 1 ) p0 $end
$var wire 1 * p1 $end
$var wire 1 + p2 $end
$var wire 1 , p3 $end
$var wire 1 # s3_saida $end
$var wire 1 3 z1 $end
$var wire 1 4 z2 $end
$var wire 1 5 z3 $end
$upscope $end
$scope module U4 $end
$var wire 1 % c1 $end
$var wire 1 $ c2 $end
$var wire 1 # c3 $end
$var wire 1 & e_saida $end
$upscope $end
$upscope $end
$upscope $end
$enddefinitions $end
$comment Show the parameter values. $end
$dumpall
$end
#0
$dumpvars
05
04
03
12
01
10
1/
1.
1-
0,
0+
0*
0)
0(
0'
0&
1%
0$
0#
b0 "
b0 !
$end
#10
0.
b100 !
1+
#20
1$
0&
11
1.
0%
0/
b1 "
1'
0+
b1000 !
1,
#30
0.
13
b1100 !
1+
#40
1#
0$
02
15
01
0-
00
14
0'
b10 "
1(
b1101 !
1)
#50
b11 "
1'
b1111 !
1*
#60
1&
12
05
1-
0#
10
04
1.
03
0'
b0 "
0(
0)
0*
b1000 !
0+
#70
0&
1$
11
00
14
0.
1/
b1 "
1'
1)
1*
1+
b111 !
0,
#80
1&
0$
01
0-
1.
b11 "
1(
0*
b1 !
0+
