categorizacao.v
module s1 (input p3, e1, e0, output s1_saida);
    nor(s1_saida, p3, e1, e0);
endmodule
module s2(input p3, p2, p1, p0, e1, e0, output s2_saida);
    wire np3, np2, ne1, z1, z2, z3;
    nor(z1, p1, p0);
    not(np3, p3);
    not(np2, p2);
    not(ne1, e1);
    or(z3, np3, np2, z1);
    and(z2, ne1, e0);
    and(s2_saida, z3, z2);
endmodule
module s3(input p3, p2, p1, p0, e1, output s3_saida);
    wire z1, z2, z3;
    and(z1, p3, p2);
    or(z2, p1, p0);
    and(z3, z2, z1);
    and(s3_saida, z3, e1);
endmodule
module error(input c1, c2, c3, output e_saida);
    nor(e_saida, c1, c2, c3);
endmodule
module circuito (
    input p3, p2, p1, p0, e1, e0,
    output c1, c2, c3, E
);

    s1 U1 (.p3(p3), .e1(e1), .e0(e0), .s1_saida(c1));
    s2 U2 (.p3(p3), .p2(p2), .p1(p1), .p0(p0), .e1(e1), .e0(e0), .s2_saida(c2));
    s3 U3 (.p3(p3), .p2(p2), .p1(p1), .p0(p0), .e1(e1), .s3_saida(c3));
    error U4 (.c1(c1), .c2(c2), .c3(c3), .e_saida(E));
endmodule

tb_completo.v
module tb_circuito;
    // Entradas do Circuito (Registradores para Fornecer Estímulos)
    reg p3, p2, p1, p0, e1, e0;
    
    // Saídas do Circuito (Wires para Capturar Respostas)
    wire c1, c2, c3, E;

    // Variáveis auxiliares para loop e contagem
    integer i_peso; // Contador de 0 a 15 para o Peso
    integer i_eixo; // Contador de 0 a 3 para o Eixo

    // CORREÇÃO DO ERRO E VISUALIZAÇÃO: Sinais concatenados e decimais
    // Usados para exibir o valor no $monitor e para simplificar a visualização
    wire [3:0] peso_bin;
    wire [1:0] eixo_bin;
    assign peso_bin = {p3, p2, p1, p0};
    assign eixo_bin = {e1, e0};
    
    // Instancia o Circuito Principal (Design Under Test - DUT)
    circuito DUT (.p3(p3), .p2(p2), .p1(p1), .p0(p0), .e1(e1), .e0(e0),
                  .c1(c1), .c2(c2), .c3(c3), .E(E));

    initial begin
        // ---------------------------------------------
        // COMANDOS PARA VISUALIZAÇÃO NO GTKWAVE
        // ---------------------------------------------
        $dumpfile("ondas.vcd"); // Cria o arquivo de formas de onda
        $dumpvars(0, tb_circuito); // Monitora todos os sinais no módulo tb_circuito
        
        // Monitora as alterações no terminal
        $monitor("t=%0d | P=%b%b%b%b (Dec: %0d) Eixo=%b%b (Dec: %0d) | C1=%b C2=%b C3=%b E=%b",
                  $time, p3, p2, p1, p0, peso_bin, e1, e0, eixo_bin, c1, c2, c3, E);

        // ---------------------------------------------
        // VARREDURA COMPLETA DE TODAS AS 64 COMBINAÇÕES
        // ---------------------------------------------

        // Loop externo: Varia o peso de 0 a 15
        for (i_peso = 0; i_peso < 16; i_peso = i_peso + 1) begin
            // Loop interno: Varia o eixo de 0 a 3
            for (i_eixo = 0; i_eixo < 4; i_eixo = i_eixo + 1) begin
                
                // Atribui os valores do loop aos pinos de entrada
                {p3, p2, p1, p0} = i_peso;
                {e1, e0} = i_eixo;
                
                // Aguarda 10 unidades de tempo para o circuito estabilizar
                #10;
            end
        end
        
        $finish; // Termina a simulação
    end
endmodule

ondas.vcd
$date
	Wed Oct 15 08:51:55 2025
$end
$version
	Icarus Verilog
$end
$timescale
	1s
$end
$scope module tb_circuito $end
$var wire 4 ! peso_bin [3:0] $end
$var wire 2 " eixo_bin [1:0] $end
$var wire 1 # c3 $end
$var wire 1 $ c2 $end
$var wire 1 % c1 $end
$var wire 1 & E $end
$var reg 1 ' e0 $end
$var reg 1 ( e1 $end
$var reg 1 ) p0 $end
$var reg 1 * p1 $end
$var reg 1 + p2 $end
$var reg 1 , p3 $end
$var integer 32 - i_eixo [31:0] $end
$var integer 32 . i_peso [31:0] $end
$scope module DUT $end
$var wire 1 ' e0 $end
$var wire 1 ( e1 $end
$var wire 1 ) p0 $end
$var wire 1 * p1 $end
$var wire 1 + p2 $end
$var wire 1 , p3 $end
$var wire 1 # c3 $end
$var wire 1 $ c2 $end
$var wire 1 % c1 $end
$var wire 1 & E $end
$scope module U1 $end
$var wire 1 ' e0 $end
$var wire 1 ( e1 $end
$var wire 1 , p3 $end
$var wire 1 % s1_saida $end
$upscope $end
$scope module U2 $end
$var wire 1 ' e0 $end
$var wire 1 ( e1 $end
$var wire 1 / ne1 $end
$var wire 1 0 np2 $end
$var wire 1 1 np3 $end
$var wire 1 ) p0 $end
$var wire 1 * p1 $end
$var wire 1 + p2 $end
$var wire 1 , p3 $end
$var wire 1 $ s2_saida $end
$var wire 1 2 z1 $end
$var wire 1 3 z2 $end
$var wire 1 4 z3 $end
$upscope $end
$scope module U3 $end
$var wire 1 ( e1 $end
$var wire 1 ) p0 $end
$var wire 1 * p1 $end
$var wire 1 + p2 $end
$var wire 1 , p3 $end
$var wire 1 # s3_saida $end
$var wire 1 5 z1 $end
$var wire 1 6 z2 $end
$var wire 1 7 z3 $end
$upscope $end
$scope module U4 $end
$var wire 1 % c1 $end
$var wire 1 $ c2 $end
$var wire 1 # c3 $end
$var wire 1 & e_saida $end
$upscope $end
$upscope $end
$upscope $end
$enddefinitions $end
$comment Show the parameter values. $end
$dumpall
$end
#0
$dumpvars
07
06
05
14
03
12
11
10
1/
b0 .
b0 -
0,
0+
0*
0)
0(
0'
0&
1%
0$
0#
b0 "
b0 !
$end
#10
1$
0%
13
b1 "
1'
b1 -
#20
1&
0$
0/
03
1(
b10 "
0'
b10 -
#30
b11 "
1'
b11 -
#40
0&
1/
1%
02
16
0(
b0 "
0'
b1 !
1)
b1 .
b0 -
#50
1$
0%
13
b1 "
1'
b1 -
#60
1&
0$
0/
03
1(
b10 "
0'
b10 -
#70
b11 "
1'
b11 -
#80
0&
1/
1%
0(
b0 "
0'
1*
b10 !
0)
b10 .
b0 -
#90
1$
0%
13
b1 "
1'
b1 -
#100
1&
0$
0/
03
1(
b10 "
0'
b10 -
#110
b11 "
1'
b11 -
#120
0&
1/
1%
0(
b0 "
0'
b11 !
1)
b11 .
b0 -
#130
1$
0%
13
b1 "
1'
b1 -
#140
1&
0$
0/
03
1(
b10 "
0'
b10 -
#150
b11 "
1'
b11 -
#160
0&
1/
1%
00
12
06
0(
b0 "
0'
1+
0*
b100 !
0)
b100 .
b0 -
#170
1$
0%
13
b1 "
1'
b1 -
#180
1&
0$
0/
03
1(
b10 "
0'
b10 -
#190
b11 "
1'
b11 -
#200
0&
1/
1%
02
16
0(
b0 "
0'
b101 !
1)
b101 .
b0 -
#210
1$
0%
13
b1 "
1'
b1 -
#220
1&
0$
0/
03
1(
b10 "
0'
b10 -
#230
b11 "
1'
b11 -
#240
0&
1/
1%
0(
b0 "
0'
1*
b110 !
0)
b110 .
b0 -
#250
1$
0%
13
b1 "
1'
b1 -
#260
1&
0$
0/
03
1(
b10 "
0'
b10 -
#270
b11 "
1'
b11 -
#280
0&
1/
1%
0(
b0 "
0'
b111 !
1)
b111 .
b0 -
#290
1$
0%
13
b1 "
1'
b1 -
#300
1&
0$
0/
03
1(
b10 "
0'
b10 -
#310
b11 "
1'
b11 -
#320
1/
01
10
12
06
0(
b0 "
0'
1,
0+
0*
b1000 !
0)
b1000 .
b0 -
#330
0&
1$
13
b1 "
1'
b1 -
#340
1&
0$
0/
03
1(
b10 "
0'
b10 -
#350
b11 "
1'
b11 -
#360
1/
02
16
0(
b0 "
0'
b1001 !
1)
b1001 .
b0 -
#370
0&
1$
13
b1 "
1'
b1 -
#380
1&
0$
0/
03
1(
b10 "
0'
b10 -
#390
b11 "
1'
b11 -
#400
1/
0(
b0 "
0'
1*
b1010 !
0)
b1010 .
b0 -
#410
0&
1$
13
b1 "
1'
b1 -
#420
1&
0$
0/
03
1(
b10 "
0'
b10 -
#430
b11 "
1'
b11 -
#440
1/
0(
b0 "
0'
b1011 !
1)
b1011 .
b0 -
#450
0&
1$
13
b1 "
1'
b1 -
#460
1&
0$
0/
03
1(
b10 "
0'
b10 -
#470
b11 "
1'
b11 -
#480
1/
00
15
12
06
0(
b0 "
0'
1+
0*
b1100 !
0)
b1100 .
b0 -
#490
0&
1$
13
b1 "
1'
b1 -
#500
1&
0$
0/
03
1(
b10 "
0'
b10 -
#510
b11 "
1'
b11 -
#520
04
17
1/
02
16
0(
b0 "
0'
b1101 !
1)
b1101 .
b0 -
#530
13
b1 "
1'
b1 -
#540
0&
0/
1#
03
1(
b10 "
0'
b10 -
#550
b11 "
1'
b11 -
#560
1&
1/
0#
0(
b0 "
0'
1*
b1110 !
0)
b1110 .
b0 -
#570
13
b1 "
1'
b1 -
#580
0&
0/
1#
03
1(
b10 "
0'
b10 -
#590
b11 "
1'
b11 -
#600
1&
1/
0#
0(
b0 "
0'
b1111 !
1)
b1111 .
b0 -
#610
13
b1 "
1'
b1 -
#620
0&
0/
1#
03
1(
b10 "
0'
b10 -
#630
b11 "
1'
b11 -
#640
b10000 .
b100 -
